nonebot_plugin_flexperm/__init__.py
nonebot_plugin_flexperm/__init__.pyi
nonebot_plugin_flexperm/adapters.py
nonebot_plugin_flexperm/check.py
nonebot_plugin_flexperm/cmds.py
nonebot_plugin_flexperm/config.py
nonebot_plugin_flexperm/core.py
nonebot_plugin_flexperm/defaults.yml
nonebot_plugin_flexperm/plugin.py
nonebot_plugin_flexperm/util.py
nonebot_plugin_flexperm-0.7.0.dist-info/LICENSE
nonebot_plugin_flexperm-0.7.0.dist-info/METADATA
nonebot_plugin_flexperm-0.7.0.dist-info/WHEEL
nonebot_plugin_flexperm-0.7.0.dist-info/RECORD
