Metadata-Version: 2.1
Name: nonebot-plugin-flexperm
Version: 0.7.0
Summary: 精细化的 NoneBot 权限管理插件
Home-page: https://github.com/rmuchan/nonebot-plugin-flexperm
License: MIT
Keywords: nonebot
Author: Muchan
Author-email: liuzh1773@buaa.edu.cn
Requires-Python: >=3.8,<4.0
Classifier: License :: OSI Approved :: MIT License
Classifier: Programming Language :: Python :: 3
Classifier: Programming Language :: Python :: 3.8
Classifier: Programming Language :: Python :: 3.9
Classifier: Programming Language :: Python :: 3.10
Classifier: Programming Language :: Python :: 3.11
Requires-Dist: nonebot-plugin-apscheduler (>=0.2.0,<0.3.0)
Requires-Dist: nonebot2 (>=2.0.0,<3.0.0)
Requires-Dist: ruamel.yaml (>=0.17.10,<0.18.0)
Project-URL: Repository, https://github.com/rmuchan/nonebot-plugin-flexperm
